{
  "averageOutDegree": 7.509641873278237,
  "path_length_50_percentile": 37,
  "path_length_20_percentile": 7,
  "path_length_80_percentile": 122,
  "averageInDegree": 7.509641873278237,
  "path_length_10_percentile": 4,
  "decentralized_average_num_unique_nodes": 37.50516647531573,
  "random_average_decentralized_path_length": 138.40334378265413,
  "hierarchy_num_nodes": 386,
  "random_average_num_unique_nodes": 109.28108672936258,
  "path_length_60_percentile": 54,
  "numNodes": 726,
  "path_length_90_percentile": 192,
  "random_num_paths_missing": 43,
  "numEdges": 5452,
  "path_length_70_percentile": 84,
  "decentralized_num_paths_found": 871,
  "selfLinks": 6,
  "decentralized_num_paths_missing": 129,
  "hierarchy_num_levels": 7,
  "random_num_paths_found": 957,
  "path_length_40_percentile": 20,
  "decentralized_average_decentralized_path_length": 71.29506314580941,
  "path_length_30_percentile": 10,
  "averagePathLength": 2.389565878217916
}