{
  "decentralized_num_paths_found": 828,
  "selfLinks": 16,
  "averageOutDegree": 4.755,
  "numNodes": 200,
  "path_length_10_percentile": 3,
  "random_num_paths_found": 964,
  "numEdges": 951,
  "averageInDegree": 4.755,
  "path_length_50_percentile": 15,
  "path_length_40_percentile": 10,
  "path_length_60_percentile": 18,
  "hierarchy_num_levels": 4,
  "path_length_90_percentile": 70,
  "decentralized_average_decentralized_path_length": 28.241545893719806,
  "path_length_80_percentile": 31,
  "path_length_30_percentile": 7,
  "random_average_decentralized_path_length": 39.40145228215768,
  "decentralized_num_paths_missing": 172,
  "path_length_70_percentile": 21,
  "random_average_num_unique_nodes": 30.36721991701245,
  "hierarchy_num_nodes": 156,
  "decentralized_average_num_unique_nodes": 17.580917874396135,
  "random_num_paths_missing": 36,
  "averagePathLength": 2.4527386934673365,
  "path_length_20_percentile": 4
}