{
    "edges": [
        {
            "source": "George Bluth",
            "target": "The apartment"
        },
        {
            "source": "George Bluth",
            "target": "Pilot"
        },
        {
            "source": "George Bluth",
            "target": "Development Arrested"
        },
        {
            "source": "George Bluth",
            "target": "Bluth Family"
        },
        {
            "source": "George Bluth",
            "target": "Lucille"
        },
        {
            "source": "George Bluth",
            "target": "Michael Bluth"
        },
        {
            "source": "George Bluth",
            "target": "Larry Mittleman"
        },
        {
            "source": "Season Three",
            "target": "George Michael"
        },
        {
            "source": "Season Three",
            "target": "George Sr."
        },
        {
            "source": "Season Three",
            "target": "Development Arrested"
        },
        {
            "source": "Season Three",
            "target": "Arrested Development"
        },
        {
            "source": "Season Three",
            "target": "Mitchell Hurwitz"
        },
        {
            "source": "Season Three",
            "target": "Michael"
        },
        {
            "source": "Reno",
            "target": "George Michael"
        },
        {
            "source": "Reno",
            "target": "Kitty"
        },
        {
            "source": "Reno",
            "target": "George Bluth"
        },
        {
            "source": "Reno",
            "target": "Tobias"
        },
        {
            "source": "Reno",
            "target": "Michael Bluth"
        },
        {
            "source": "My Mother, The Car",
            "target": "My Mother, the Car"
        },
        {
            "source": "George Michael",
            "target": "George Michael Bluth"
        },
        {
            "source": "Transcript of Meat the Veals",
            "target": "Season Two"
        },
        {
            "source": "Lemon grove",
            "target": "Lucille"
        },
        {
            "source": "Lemon grove",
            "target": "Michael"
        },
        {
            "source": "Lemon grove",
            "target": "Oscar"
        },
        {
            "source": "List of episodes",
            "target": "My Mother, The Car"
        },
        {
            "source": "List of episodes",
            "target": "Best Man for the GOB"
        },
        {
            "source": "List of episodes",
            "target": "Development Arrested"
        },
        {
            "source": "List of episodes",
            "target": "Pilot"
        },
        {
            "source": "Transcript of Spring Breakout",
            "target": "Jeff Garlin"
        },
        {
            "source": "Transcript of Spring Breakout",
            "target": "Season Two"
        },
        {
            "source": "Nichael",
            "target": "Michael Bluth"
        },
        {
            "source": "Season Two",
            "target": "George Sr."
        },
        {
            "source": "Season Two",
            "target": "Season One"
        },
        {
            "source": "Season Two",
            "target": "Arrested Development"
        },
        {
            "source": "Season Two",
            "target": "Mitchell Hurwitz"
        },
        {
            "source": "Season Two",
            "target": "Tobias"
        },
        {
            "source": "Season Two",
            "target": "Michael"
        },
        {
            "source": "1x8",
            "target": "My Mother, the Car"
        },
        {
            "source": "George Michael Bluth",
            "target": "Ann"
        },
        {
            "source": "George Michael Bluth",
            "target": "Pilot"
        },
        {
            "source": "George Michael Bluth",
            "target": "Development Arrested"
        },
        {
            "source": "George Michael Bluth",
            "target": "Michael Bluth"
        },
        {
            "source": "George Michael Bluth",
            "target": "Bluth Family"
        },
        {
            "source": "George Michael Bluth",
            "target": "Model House"
        },
        {
            "source": "George Michael Bluth",
            "target": "Banana Stand"
        },
        {
            "source": "George Michael Bluth",
            "target": "Michael"
        },
        {
            "source": "Gcheung28/Arrested Development's Return Date",
            "target": "Arrested Development"
        },
        {
            "source": "Transcript of Motherboy XXX",
            "target": "Season Two"
        },
        {
            "source": "Transcript of Motherboy XXX",
            "target": "Mitchell Hurwitz"
        },
        {
            "source": "The Cockroach",
            "target": "Arrested Development"
        },
        {
            "source": "The Cockroach",
            "target": "Michael Bluth"
        },
        {
            "source": "Peanut brittle",
            "target": "George Bluth"
        },
        {
            "source": "Arrested Development Wiki",
            "target": "Main Page"
        },
        {
            "source": "Nichael Bluth",
            "target": "Michael Bluth"
        },
        {
            "source": "Home",
            "target": "Main Page"
        },
        {
            "source": "Afternoon Deelite",
            "target": "Lucille"
        },
        {
            "source": "Afternoon Deelite",
            "target": "Michael"
        },
        {
            "source": "Herb Zuckerkorn",
            "target": "Lucille"
        },
        {
            "source": "Herb Zuckerkorn",
            "target": "Barry"
        },
        {
            "source": "Herb Zuckerkorn",
            "target": "George Bluth"
        },
        {
            "source": "Cookies scented spray",
            "target": "James"
        },
        {
            "source": "Freddie Wilson",
            "target": "Lindsay"
        },
        {
            "source": "Freddie Wilson",
            "target": "George Michael"
        },
        {
            "source": "Freddie Wilson",
            "target": "Tobias"
        },
        {
            "source": "Freddie Wilson",
            "target": "Michael"
        },
        {
            "source": "Mural",
            "target": "Arrested Development"
        },
        {
            "source": "Mural",
            "target": "Michael"
        },
        {
            "source": "Jeff Garlin",
            "target": "Season Three"
        },
        {
            "source": "Jeff Garlin",
            "target": "Arrested Development"
        },
        {
            "source": "Jeff Garlin",
            "target": "Development Arrested"
        },
        {
            "source": "Jeff Garlin",
            "target": "Season Two"
        },
        {
            "source": "My Mother, the Car",
            "target": "FOX"
        },
        {
            "source": "My Mother, the Car",
            "target": "Development Arrested"
        },
        {
            "source": "My Mother, the Car",
            "target": "Michael Bluth"
        },
        {
            "source": "My Mother, the Car",
            "target": "My Mother the Car"
        },
        {
            "source": "My Mother, the Car",
            "target": "George Michael Bluth"
        },
        {
            "source": "My Mother, the Car",
            "target": "Lindsay F\u00fcnke"
        },
        {
            "source": "My Mother, the Car",
            "target": "George Bluth Sr."
        },
        {
            "source": "3x13",
            "target": "Development Arrested"
        },
        {
            "source": "Arrested Development bobbleheads",
            "target": "Michael"
        },
        {
            "source": "Pilot",
            "target": "George Bluth Sr."
        },
        {
            "source": "Pilot",
            "target": "Michael Bluth"
        },
        {
            "source": "Transcript of Burning Love",
            "target": "Season Two"
        },
        {
            "source": "Transcript of Burning Love",
            "target": "Michael"
        },
        {
            "source": "John Fortenberry",
            "target": "Season Three"
        },
        {
            "source": "John Fortenberry",
            "target": "Arrested Development"
        },
        {
            "source": "John Fortenberry",
            "target": "Development Arrested"
        },
        {
            "source": "John Fortenberry",
            "target": "Season One"
        },
        {
            "source": "1x01",
            "target": "Pilot"
        },
        {
            "source": "Michael",
            "target": "Michael Bluth"
        },
        {
            "source": "Transcript of Afternoon Delight",
            "target": "Season Two"
        },
        {
            "source": "Transcript of Hand to God",
            "target": "Season Two"
        },
        {
            "source": "Transcript of Hand to God",
            "target": "Mitchell Hurwitz"
        },
        {
            "source": "Arrested Development Netflix Premiere",
            "target": "2013 Netflix Orange Carpet Season Four Premiere"
        },
        {
            "source": "Transcript of Good Grief",
            "target": "Season Two"
        },
        {
            "source": "Season One",
            "target": "Lucille 2"
        },
        {
            "source": "Season One",
            "target": "George Michael"
        },
        {
            "source": "Season One",
            "target": "George Sr."
        },
        {
            "source": "Season One",
            "target": "Lindsay"
        },
        {
            "source": "Season One",
            "target": "Lucille"
        },
        {
            "source": "Season One",
            "target": "Mitchell Hurwitz"
        },
        {
            "source": "Season One",
            "target": "Michael Bluth"
        },
        {
            "source": "Season One",
            "target": "Arrested Development"
        },
        {
            "source": "Season One",
            "target": "Tobias"
        },
        {
            "source": "Michael Bluth",
            "target": "Ann"
        },
        {
            "source": "Michael Bluth",
            "target": "George Michael"
        },
        {
            "source": "Michael Bluth",
            "target": "George Michael Bluth"
        },
        {
            "source": "Michael Bluth",
            "target": "Development Arrested"
        },
        {
            "source": "Michael Bluth",
            "target": "Pilot"
        },
        {
            "source": "Michael Bluth",
            "target": "Lindsay"
        },
        {
            "source": "Michael Bluth",
            "target": "Bluth Family"
        },
        {
            "source": "Michael Bluth",
            "target": "Annyong"
        },
        {
            "source": "Michael Bluth",
            "target": "Arrested Development"
        },
        {
            "source": "Michael Bluth",
            "target": "George Sr."
        },
        {
            "source": "Michael Bluth",
            "target": "The Model Home"
        },
        {
            "source": "Chareth Richter",
            "target": "Michael"
        },
        {
            "source": "Transcript of The Cabin Show",
            "target": "Season Three"
        },
        {
            "source": "Transcript of The Cabin Show",
            "target": "Mitchell Hurwitz"
        },
        {
            "source": "Pete the mailman",
            "target": "George Michael"
        },
        {
            "source": "Pete the mailman",
            "target": "Michael Bluth"
        },
        {
            "source": "George Sr.",
            "target": "George Bluth Sr."
        },
        {
            "source": "UnLead News",
            "target": "George Michael"
        },
        {
            "source": "UnLead News",
            "target": "John Beard's To Entrap a Local Predator: Orange County Edition: Super Creep"
        },
        {
            "source": "Transcript of Ready, Aim, Marry Me",
            "target": "Season Two"
        },
        {
            "source": "Transcript of Ready, Aim, Marry Me",
            "target": "Mitchell Hurwitz"
        },
        {
            "source": "George, Sr.",
            "target": "George Bluth"
        },
        {
            "source": "Dr. Sandor Plumb",
            "target": "Michael Bluth"
        },
        {
            "source": "Dr. Sandor Plumb",
            "target": "The Plumb Clinic"
        },
        {
            "source": "Los Mas Buscados de Mexico",
            "target": "George Bluth"
        },
        {
            "source": "My Mother the Car",
            "target": "My Mother, the Car"
        },
        {
            "source": "Main Page",
            "target": "Tobias Funke"
        },
        {
            "source": "Main Page",
            "target": "Development Arrested"
        },
        {
            "source": "Main Page",
            "target": "Michael Bluth"
        },
        {
            "source": "Main Page",
            "target": "Arrested Development"
        },
        {
            "source": "Main Page",
            "target": "List of episodes"
        },
        {
            "source": "Main Page",
            "target": "Tobias"
        },
        {
            "source": "Main Page",
            "target": "Michael"
        },
        {
            "source": "The Plumb Clinic",
            "target": "Dr. Sandor Plumb"
        },
        {
            "source": "The Plumb Clinic",
            "target": "Michael Bluth"
        },
        {
            "source": "Seth Rogen",
            "target": "George Bluth"
        },
        {
            "source": "Austero Bluth Company",
            "target": "Michael Bluth"
        },
        {
            "source": "Max Winkler",
            "target": "Arrested Development"
        },
        {
            "source": "Fox.com/arresteddev",
            "target": "Season Two"
        },
        {
            "source": "Fox.com/arresteddev",
            "target": "Arrested Development"
        },
        {
            "source": "Fox.com/arresteddev",
            "target": "Season Three"
        },
        {
            "source": "Fox.com/arresteddev",
            "target": "Season One"
        },
        {
            "source": "Fox.com/arresteddev",
            "target": "Michael"
        },
        {
            "source": "Transcript of Queen for a Day",
            "target": "Jeff Garlin"
        },
        {
            "source": "Transcript of Queen for a Day",
            "target": "Season Two"
        },
        {
            "source": "Development Arrested",
            "target": "Lindsay"
        },
        {
            "source": "Development Arrested",
            "target": "Pilot"
        },
        {
            "source": "Development Arrested",
            "target": "Ann"
        },
        {
            "source": "Development Arrested",
            "target": "Arrested Development"
        },
        {
            "source": "Development Arrested",
            "target": "Mitchell Hurwitz"
        },
        {
            "source": "Development Arrested",
            "target": "Best Man for the GOB"
        },
        {
            "source": "Development Arrested",
            "target": "Michael"
        },
        {
            "source": "Development Arrested",
            "target": "My Mother, The Car"
        },
        {
            "source": "Development Arrested",
            "target": "George Michael"
        },
        {
            "source": "Development Arrested",
            "target": "George Sr."
        },
        {
            "source": "Development Arrested",
            "target": "Mort"
        },
        {
            "source": "Development Arrested",
            "target": "Annyong"
        },
        {
            "source": "Development Arrested",
            "target": "Jeff Garlin"
        },
        {
            "source": "Development Arrested",
            "target": "Lucille"
        },
        {
            "source": "Development Arrested",
            "target": "John Fortenberry"
        },
        {
            "source": "1x08",
            "target": "My Mother, the Car"
        },
        {
            "source": "Transcript of Righteous Brothers",
            "target": "Jeff Garlin"
        },
        {
            "source": "Transcript of Righteous Brothers",
            "target": "Season Two"
        },
        {
            "source": "Transcript of Righteous Brothers",
            "target": "Mitchell Hurwitz"
        },
        {
            "source": "Black Friday",
            "target": "George Bluth"
        },
        {
            "source": "George Bluth Sr.",
            "target": "George Bluth"
        },
        {
            "source": "George",
            "target": "George Bluth Sr."
        },
        {
            "source": "Hurwitz",
            "target": "Mitchell Hurwitz"
        }
    ],
    "directed": true,
    "multigraph": false,
    "nodes": [
        {
            "parity": 0,
            "degree": 15,
            "id": "George Bluth"
        },
        {
            "parity": 1,
            "degree": 10,
            "id": "Season Three"
        },
        {
            "parity": 0,
            "degree": 5,
            "id": "Reno"
        },
        {
            "parity": 0,
            "degree": 3,
            "id": "My Mother, The Car"
        },
        {
            "parity": 0,
            "degree": 9,
            "id": "George Michael"
        },
        {
            "parity": 0,
            "degree": 1,
            "id": "Transcript of Meat the Veals"
        },
        {
            "parity": 0,
            "degree": 1,
            "id": "Tobias Funke"
        },
        {
            "parity": 0,
            "degree": 3,
            "id": "Lemon grove"
        },
        {
            "parity": 0,
            "degree": 5,
            "id": "List of episodes"
        },
        {
            "parity": 1,
            "degree": 2,
            "id": "Transcript of Spring Breakout"
        },
        {
            "parity": 0,
            "degree": 1,
            "id": "2013 Netflix Orange Carpet Season Four Premiere"
        },
        {
            "parity": 0,
            "degree": 1,
            "id": "Nichael"
        },
        {
            "parity": 1,
            "degree": 18,
            "id": "Season Two"
        },
        {
            "parity": 0,
            "degree": 1,
            "id": "1x8"
        },
        {
            "parity": 0,
            "degree": 11,
            "id": "George Michael Bluth"
        },
        {
            "parity": 0,
            "degree": 1,
            "id": "Gcheung28/Arrested Development's Return Date"
        },
        {
            "parity": 1,
            "degree": 2,
            "id": "Transcript of Motherboy XXX"
        },
        {
            "parity": 1,
            "degree": 2,
            "id": "The Cockroach"
        },
        {
            "parity": 0,
            "degree": 1,
            "id": "Peanut brittle"
        },
        {
            "parity": 0,
            "degree": 1,
            "id": "Arrested Development Wiki"
        },
        {
            "parity": 0,
            "degree": 1,
            "id": "Nichael Bluth"
        },
        {
            "parity": 0,
            "degree": 1,
            "id": "Home"
        },
        {
            "parity": 0,
            "degree": 1,
            "id": "James"
        },
        {
            "parity": 1,
            "degree": 2,
            "id": "Afternoon Deelite"
        },
        {
            "parity": 0,
            "degree": 3,
            "id": "Herb Zuckerkorn"
        },
        {
            "parity": 0,
            "degree": 1,
            "id": "Lindsay F\u00fcnke"
        },
        {
            "parity": 0,
            "degree": 1,
            "id": "Cookies scented spray"
        },
        {
            "parity": 1,
            "degree": 4,
            "id": "Freddie Wilson"
        },
        {
            "parity": 0,
            "degree": 1,
            "id": "John Beard's To Entrap a Local Predator: Orange County Edition: Super Creep"
        },
        {
            "parity": 1,
            "degree": 2,
            "id": "Mural"
        },
        {
            "parity": 1,
            "degree": 8,
            "id": "Jeff Garlin"
        },
        {
            "parity": 0,
            "degree": 11,
            "id": "My Mother, the Car"
        },
        {
            "parity": 0,
            "degree": 1,
            "id": "3x13"
        },
        {
            "parity": 0,
            "degree": 1,
            "id": "Arrested Development bobbleheads"
        },
        {
            "parity": 1,
            "degree": 8,
            "id": "Pilot"
        },
        {
            "parity": 1,
            "degree": 2,
            "id": "Transcript of Burning Love"
        },
        {
            "parity": 0,
            "degree": 5,
            "id": "John Fortenberry"
        },
        {
            "parity": 1,
            "degree": 10,
            "id": "Mitchell Hurwitz"
        },
        {
            "parity": 0,
            "degree": 1,
            "id": "1x01"
        },
        {
            "parity": 1,
            "degree": 14,
            "id": "Michael"
        },
        {
            "parity": 0,
            "degree": 1,
            "id": "Transcript of Afternoon Delight"
        },
        {
            "parity": 0,
            "degree": 1,
            "id": "FOX"
        },
        {
            "parity": 1,
            "degree": 2,
            "id": "Transcript of Hand to God"
        },
        {
            "parity": 0,
            "degree": 5,
            "id": "Tobias"
        },
        {
            "parity": 0,
            "degree": 1,
            "id": "Mort"
        },
        {
            "parity": 0,
            "degree": 1,
            "id": "Arrested Development Netflix Premiere"
        },
        {
            "parity": 0,
            "degree": 1,
            "id": "Transcript of Good Grief"
        },
        {
            "parity": 0,
            "degree": 1,
            "id": "Oscar"
        },
        {
            "parity": 1,
            "degree": 2,
            "id": "Best Man for the GOB"
        },
        {
            "parity": 1,
            "degree": 12,
            "id": "Season One"
        },
        {
            "parity": 0,
            "degree": 1,
            "id": "The apartment"
        },
        {
            "parity": 1,
            "degree": 26,
            "id": "Michael Bluth"
        },
        {
            "parity": 0,
            "degree": 1,
            "id": "Chareth Richter"
        },
        {
            "parity": 1,
            "degree": 2,
            "id": "Transcript of The Cabin Show"
        },
        {
            "parity": 1,
            "degree": 2,
            "id": "Pete the mailman"
        },
        {
            "parity": 1,
            "degree": 6,
            "id": "George Sr."
        },
        {
            "parity": 1,
            "degree": 2,
            "id": "UnLead News"
        },
        {
            "parity": 1,
            "degree": 2,
            "id": "Annyong"
        },
        {
            "parity": 1,
            "degree": 2,
            "id": "Transcript of Ready, Aim, Marry Me"
        },
        {
            "parity": 0,
            "degree": 1,
            "id": "George, Sr."
        },
        {
            "parity": 0,
            "degree": 3,
            "id": "Dr. Sandor Plumb"
        },
        {
            "parity": 0,
            "degree": 3,
            "id": "Ann"
        },
        {
            "parity": 0,
            "degree": 13,
            "id": "Arrested Development"
        },
        {
            "parity": 0,
            "degree": 1,
            "id": "Los Mas Buscados de Mexico"
        },
        {
            "parity": 0,
            "degree": 1,
            "id": "Barry"
        },
        {
            "parity": 1,
            "degree": 2,
            "id": "My Mother the Car"
        },
        {
            "parity": 0,
            "degree": 1,
            "id": "Banana Stand"
        },
        {
            "parity": 1,
            "degree": 4,
            "id": "Lindsay"
        },
        {
            "parity": 0,
            "degree": 1,
            "id": "Model House"
        },
        {
            "parity": 0,
            "degree": 9,
            "id": "Main Page"
        },
        {
            "parity": 0,
            "degree": 3,
            "id": "The Plumb Clinic"
        },
        {
            "parity": 0,
            "degree": 1,
            "id": "Seth Rogen"
        },
        {
            "parity": 0,
            "degree": 1,
            "id": "Austero Bluth Company"
        },
        {
            "parity": 0,
            "degree": 1,
            "id": "Max Winkler"
        },
        {
            "parity": 0,
            "degree": 5,
            "id": "Fox.com/arresteddev"
        },
        {
            "parity": 1,
            "degree": 2,
            "id": "Transcript of Queen for a Day"
        },
        {
            "parity": 0,
            "degree": 3,
            "id": "Bluth Family"
        },
        {
            "parity": 0,
            "degree": 25,
            "id": "Development Arrested"
        },
        {
            "parity": 0,
            "degree": 1,
            "id": "1x08"
        },
        {
            "parity": 0,
            "degree": 3,
            "id": "Transcript of Righteous Brothers"
        },
        {
            "parity": 0,
            "degree": 1,
            "id": "Black Friday"
        },
        {
            "parity": 0,
            "degree": 5,
            "id": "George Bluth Sr."
        },
        {
            "parity": 0,
            "degree": 1,
            "id": "The Model Home"
        },
        {
            "parity": 0,
            "degree": 1,
            "id": "Kitty"
        },
        {
            "parity": 0,
            "degree": 1,
            "id": "Larry Mittleman"
        },
        {
            "parity": 0,
            "degree": 1,
            "id": "Lucille 2"
        },
        {
            "parity": 0,
            "degree": 1,
            "id": "George"
        },
        {
            "parity": 1,
            "degree": 6,
            "id": "Lucille"
        },
        {
            "parity": 0,
            "degree": 1,
            "id": "Hurwitz"
        }
    ],
    "links": [
        {
            "source": 0,
            "target": 50
        },
        {
            "source": 0,
            "target": 34
        },
        {
            "source": 0,
            "target": 77
        },
        {
            "source": 0,
            "target": 76
        },
        {
            "source": 0,
            "target": 87
        },
        {
            "source": 0,
            "target": 51
        },
        {
            "source": 0,
            "target": 84
        },
        {
            "source": 1,
            "target": 4
        },
        {
            "source": 1,
            "target": 55
        },
        {
            "source": 1,
            "target": 77
        },
        {
            "source": 1,
            "target": 62
        },
        {
            "source": 1,
            "target": 37
        },
        {
            "source": 1,
            "target": 39
        },
        {
            "source": 2,
            "target": 4
        },
        {
            "source": 2,
            "target": 83
        },
        {
            "source": 2,
            "target": 0
        },
        {
            "source": 2,
            "target": 43
        },
        {
            "source": 2,
            "target": 51
        },
        {
            "source": 3,
            "target": 31
        },
        {
            "source": 4,
            "target": 14
        },
        {
            "source": 5,
            "target": 12
        },
        {
            "source": 7,
            "target": 87
        },
        {
            "source": 7,
            "target": 39
        },
        {
            "source": 7,
            "target": 47
        },
        {
            "source": 8,
            "target": 3
        },
        {
            "source": 8,
            "target": 48
        },
        {
            "source": 8,
            "target": 77
        },
        {
            "source": 8,
            "target": 34
        },
        {
            "source": 9,
            "target": 30
        },
        {
            "source": 9,
            "target": 12
        },
        {
            "source": 11,
            "target": 51
        },
        {
            "source": 12,
            "target": 55
        },
        {
            "source": 12,
            "target": 49
        },
        {
            "source": 12,
            "target": 62
        },
        {
            "source": 12,
            "target": 37
        },
        {
            "source": 12,
            "target": 43
        },
        {
            "source": 12,
            "target": 39
        },
        {
            "source": 13,
            "target": 31
        },
        {
            "source": 14,
            "target": 61
        },
        {
            "source": 14,
            "target": 34
        },
        {
            "source": 14,
            "target": 77
        },
        {
            "source": 14,
            "target": 51
        },
        {
            "source": 14,
            "target": 76
        },
        {
            "source": 14,
            "target": 68
        },
        {
            "source": 14,
            "target": 66
        },
        {
            "source": 14,
            "target": 39
        },
        {
            "source": 15,
            "target": 62
        },
        {
            "source": 16,
            "target": 12
        },
        {
            "source": 16,
            "target": 37
        },
        {
            "source": 17,
            "target": 62
        },
        {
            "source": 17,
            "target": 51
        },
        {
            "source": 18,
            "target": 0
        },
        {
            "source": 19,
            "target": 69
        },
        {
            "source": 20,
            "target": 51
        },
        {
            "source": 21,
            "target": 69
        },
        {
            "source": 23,
            "target": 87
        },
        {
            "source": 23,
            "target": 39
        },
        {
            "source": 24,
            "target": 87
        },
        {
            "source": 24,
            "target": 64
        },
        {
            "source": 24,
            "target": 0
        },
        {
            "source": 26,
            "target": 22
        },
        {
            "source": 27,
            "target": 67
        },
        {
            "source": 27,
            "target": 4
        },
        {
            "source": 27,
            "target": 43
        },
        {
            "source": 27,
            "target": 39
        },
        {
            "source": 29,
            "target": 62
        },
        {
            "source": 29,
            "target": 39
        },
        {
            "source": 30,
            "target": 1
        },
        {
            "source": 30,
            "target": 62
        },
        {
            "source": 30,
            "target": 77
        },
        {
            "source": 30,
            "target": 12
        },
        {
            "source": 31,
            "target": 41
        },
        {
            "source": 31,
            "target": 77
        },
        {
            "source": 31,
            "target": 51
        },
        {
            "source": 31,
            "target": 65
        },
        {
            "source": 31,
            "target": 14
        },
        {
            "source": 31,
            "target": 25
        },
        {
            "source": 31,
            "target": 81
        },
        {
            "source": 32,
            "target": 77
        },
        {
            "source": 33,
            "target": 39
        },
        {
            "source": 34,
            "target": 81
        },
        {
            "source": 34,
            "target": 51
        },
        {
            "source": 35,
            "target": 12
        },
        {
            "source": 35,
            "target": 39
        },
        {
            "source": 36,
            "target": 1
        },
        {
            "source": 36,
            "target": 62
        },
        {
            "source": 36,
            "target": 77
        },
        {
            "source": 36,
            "target": 49
        },
        {
            "source": 38,
            "target": 34
        },
        {
            "source": 39,
            "target": 51
        },
        {
            "source": 40,
            "target": 12
        },
        {
            "source": 42,
            "target": 12
        },
        {
            "source": 42,
            "target": 37
        },
        {
            "source": 45,
            "target": 10
        },
        {
            "source": 46,
            "target": 12
        },
        {
            "source": 49,
            "target": 85
        },
        {
            "source": 49,
            "target": 4
        },
        {
            "source": 49,
            "target": 55
        },
        {
            "source": 49,
            "target": 67
        },
        {
            "source": 49,
            "target": 87
        },
        {
            "source": 49,
            "target": 37
        },
        {
            "source": 49,
            "target": 51
        },
        {
            "source": 49,
            "target": 62
        },
        {
            "source": 49,
            "target": 43
        },
        {
            "source": 51,
            "target": 61
        },
        {
            "source": 51,
            "target": 4
        },
        {
            "source": 51,
            "target": 14
        },
        {
            "source": 51,
            "target": 77
        },
        {
            "source": 51,
            "target": 34
        },
        {
            "source": 51,
            "target": 67
        },
        {
            "source": 51,
            "target": 76
        },
        {
            "source": 51,
            "target": 57
        },
        {
            "source": 51,
            "target": 62
        },
        {
            "source": 51,
            "target": 55
        },
        {
            "source": 51,
            "target": 82
        },
        {
            "source": 52,
            "target": 39
        },
        {
            "source": 53,
            "target": 1
        },
        {
            "source": 53,
            "target": 37
        },
        {
            "source": 54,
            "target": 4
        },
        {
            "source": 54,
            "target": 51
        },
        {
            "source": 55,
            "target": 81
        },
        {
            "source": 56,
            "target": 4
        },
        {
            "source": 56,
            "target": 28
        },
        {
            "source": 58,
            "target": 12
        },
        {
            "source": 58,
            "target": 37
        },
        {
            "source": 59,
            "target": 0
        },
        {
            "source": 60,
            "target": 51
        },
        {
            "source": 60,
            "target": 70
        },
        {
            "source": 63,
            "target": 0
        },
        {
            "source": 65,
            "target": 31
        },
        {
            "source": 69,
            "target": 6
        },
        {
            "source": 69,
            "target": 77
        },
        {
            "source": 69,
            "target": 51
        },
        {
            "source": 69,
            "target": 62
        },
        {
            "source": 69,
            "target": 8
        },
        {
            "source": 69,
            "target": 43
        },
        {
            "source": 69,
            "target": 39
        },
        {
            "source": 70,
            "target": 60
        },
        {
            "source": 70,
            "target": 51
        },
        {
            "source": 71,
            "target": 0
        },
        {
            "source": 72,
            "target": 51
        },
        {
            "source": 73,
            "target": 62
        },
        {
            "source": 74,
            "target": 12
        },
        {
            "source": 74,
            "target": 62
        },
        {
            "source": 74,
            "target": 1
        },
        {
            "source": 74,
            "target": 49
        },
        {
            "source": 74,
            "target": 39
        },
        {
            "source": 75,
            "target": 30
        },
        {
            "source": 75,
            "target": 12
        },
        {
            "source": 77,
            "target": 67
        },
        {
            "source": 77,
            "target": 34
        },
        {
            "source": 77,
            "target": 61
        },
        {
            "source": 77,
            "target": 62
        },
        {
            "source": 77,
            "target": 37
        },
        {
            "source": 77,
            "target": 48
        },
        {
            "source": 77,
            "target": 39
        },
        {
            "source": 77,
            "target": 3
        },
        {
            "source": 77,
            "target": 4
        },
        {
            "source": 77,
            "target": 55
        },
        {
            "source": 77,
            "target": 44
        },
        {
            "source": 77,
            "target": 57
        },
        {
            "source": 77,
            "target": 30
        },
        {
            "source": 77,
            "target": 87
        },
        {
            "source": 77,
            "target": 36
        },
        {
            "source": 78,
            "target": 31
        },
        {
            "source": 79,
            "target": 30
        },
        {
            "source": 79,
            "target": 12
        },
        {
            "source": 79,
            "target": 37
        },
        {
            "source": 80,
            "target": 0
        },
        {
            "source": 81,
            "target": 0
        },
        {
            "source": 86,
            "target": 81
        },
        {
            "source": 88,
            "target": 37
        }
    ],
    "graph": {},
    "basic": {
        "numEdges": 172,
        "averagePathLength": 2.5845588235294117,
        "averageOutDegree": 1.9325842696629214,
        "numNodes": 89,
        "selfLinks": 0,
        "averageInDegree": 1.9325842696629214
    }
}