{
    "edges": [
        {
            "source": "Creeps",
            "target": "Minion"
        },
        {
            "source": "Ancient Golem",
            "target": "Summoner's Rift"
        },
        {
            "source": "Creep",
            "target": "Minion"
        },
        {
            "source": "Riot Games Inc.",
            "target": "League of Legends"
        },
        {
            "source": "Minion",
            "target": "Dragon"
        },
        {
            "source": "Minion",
            "target": "LoL"
        },
        {
            "source": "Minion",
            "target": "Wraith"
        },
        {
            "source": "Summoner's Rift",
            "target": "Dragon"
        },
        {
            "source": "Summoner's Rift",
            "target": "Wraith"
        },
        {
            "source": "Dragon",
            "target": "Summoner's Rift"
        },
        {
            "source": "Summoners",
            "target": "Summoner"
        },
        {
            "source": "Item",
            "target": "Meki Pendant"
        },
        {
            "source": "Item",
            "target": "Blue Pill"
        },
        {
            "source": "Item",
            "target": "Tear of the Goddess"
        },
        {
            "source": "Item",
            "target": "Infinity Edge"
        },
        {
            "source": "Item",
            "target": "Glacial Shroud"
        },
        {
            "source": "Field of Justice",
            "target": "Summoner's Rift"
        },
        {
            "source": "Wraith",
            "target": "Summoner's Rift"
        }
    ],
    "directed": true,
    "multigraph": false,
    "nodes": [
        {
            "parity": 0,
            "degree": 1,
            "id": "Meki Pendant"
        },
        {
            "parity": 0,
            "degree": 1,
            "id": "Creeps"
        },
        {
            "parity": 0,
            "degree": 1,
            "id": "Ancient Golem"
        },
        {
            "parity": 0,
            "degree": 1,
            "id": "Creep"
        },
        {
            "parity": 0,
            "degree": 1,
            "id": "Blue Pill"
        },
        {
            "parity": 0,
            "degree": 1,
            "id": "Riot Games Inc."
        },
        {
            "parity": 0,
            "degree": 1,
            "id": "League of Legends"
        },
        {
            "parity": 0,
            "degree": 1,
            "id": "LoL"
        },
        {
            "parity": 0,
            "degree": 5,
            "id": "Minion"
        },
        {
            "parity": 0,
            "degree": 1,
            "id": "Tear of the Goddess"
        },
        {
            "parity": 0,
            "degree": 1,
            "id": "Infinity Edge"
        },
        {
            "parity": 1,
            "degree": 6,
            "id": "Summoner's Rift"
        },
        {
            "parity": 0,
            "degree": 3,
            "id": "Dragon"
        },
        {
            "parity": 0,
            "degree": 1,
            "id": "Summoners"
        },
        {
            "parity": 0,
            "degree": 5,
            "id": "Item"
        },
        {
            "parity": 0,
            "degree": 1,
            "id": "Summoner"
        },
        {
            "parity": 0,
            "degree": 1,
            "id": "Field of Justice"
        },
        {
            "parity": 0,
            "degree": 3,
            "id": "Wraith"
        },
        {
            "parity": 0,
            "degree": 1,
            "id": "Glacial Shroud"
        }
    ],
    "links": [
        {
            "source": 1,
            "target": 8
        },
        {
            "source": 2,
            "target": 11
        },
        {
            "source": 3,
            "target": 8
        },
        {
            "source": 5,
            "target": 6
        },
        {
            "source": 8,
            "target": 12
        },
        {
            "source": 8,
            "target": 7
        },
        {
            "source": 8,
            "target": 17
        },
        {
            "source": 11,
            "target": 12
        },
        {
            "source": 11,
            "target": 17
        },
        {
            "source": 12,
            "target": 11
        },
        {
            "source": 13,
            "target": 15
        },
        {
            "source": 14,
            "target": 0
        },
        {
            "source": 14,
            "target": 4
        },
        {
            "source": 14,
            "target": 9
        },
        {
            "source": 14,
            "target": 10
        },
        {
            "source": 14,
            "target": 18
        },
        {
            "source": 16,
            "target": 11
        },
        {
            "source": 17,
            "target": 11
        }
    ],
    "graph": {},
    "basic": {
        "numEdges": 18,
        "averagePathLength": 1.3333333333333333,
        "averageOutDegree": 0.9473684210526315,
        "numNodes": 19,
        "selfLinks": 0,
        "averageInDegree": 0.9473684210526315
    }
}