{
  "path_length_80_percentile": 10,
  "random_average_decentralized_path_length": 13.874720357941834,
  "numEdges": 6619,
  "path_length_20_percentile": 3,
  "hierarchy_num_nodes": 353,
  "random_num_paths_missing": 106,
  "decentralized_average_decentralized_path_length": 9.926282051282051,
  "random_average_num_unique_nodes": 12.779642058165548,
  "path_length_30_percentile": 4,
  "hierarchy_num_levels": 5,
  "numNodes": 1001,
  "decentralized_average_num_unique_nodes": 7.360042735042735,
  "selfLinks": 3,
  "path_length_60_percentile": 6,
  "random_num_paths_found": 894,
  "path_length_90_percentile": 18,
  "path_length_70_percentile": 8,
  "path_length_40_percentile": 4,
  "path_length_10_percentile": 3,
  "averageOutDegree": 6.612387612387613,
  "decentralized_num_paths_found": 936,
  "averagePathLength": 3.613255117825502,
  "averageInDegree": 6.612387612387613,
  "decentralized_num_paths_missing": 64,
  "path_length_50_percentile": 5
}