{
  "path_length_80_percentile": 7,
  "random_average_decentralized_path_length": 10.072072072072071,
  "numEdges": 1712,
  "path_length_20_percentile": 3,
  "hierarchy_num_nodes": 116,
  "random_num_paths_missing": 1,
  "decentralized_average_decentralized_path_length": 6.777,
  "random_average_num_unique_nodes": 9.088088088088089,
  "path_length_30_percentile": 3,
  "hierarchy_num_levels": 8,
  "numNodes": 413,
  "decentralized_average_num_unique_nodes": 5.578,
  "selfLinks": 1,
  "path_length_60_percentile": 5,
  "random_num_paths_found": 999,
  "path_length_90_percentile": 11,
  "path_length_70_percentile": 6,
  "path_length_40_percentile": 4,
  "path_length_10_percentile": 3,
  "averageOutDegree": 4.145278450363196,
  "decentralized_num_paths_found": 1000,
  "averagePathLength": 3.282387747998608,
  "averageInDegree": 4.145278450363196,
  "decentralized_num_paths_missing": 0,
  "path_length_50_percentile": 4
}