{
  "numNodes": 1255,
  "random_average_decentralized_path_length": 45.28409090909091,
  "hierarchy_num_levels": 6,
  "path_length_20_percentile": 7,
  "numEdges": 11007,
  "random_average_num_unique_nodes": 41.04403409090909,
  "path_length_80_percentile": 96,
  "random_num_paths_found": 704,
  "averageInDegree": 8.770517928286852,
  "path_length_90_percentile": 138,
  "hierarchy_num_nodes": 556,
  "path_length_10_percentile": 4,
  "selfLinks": 8,
  "path_length_30_percentile": 11,
  "decentralized_average_decentralized_path_length": 46.087671232876716,
  "decentralized_num_paths_found": 730,
  "decentralized_num_paths_missing": 270,
  "random_num_paths_missing": 296,
  "path_length_40_percentile": 17,
  "path_length_50_percentile": 23,
  "path_length_70_percentile": 45,
  "path_length_60_percentile": 31,
  "averageOutDegree": 8.770517928286852,
  "decentralized_average_num_unique_nodes": 30.512328767123286,
  "averagePathLength": 3.5772928391285923
}