{
  "numNodes": 727,
  "numEdges": 5525,
  "averageInDegree": 7.599724896836314,
  "averageOutDegree": 7.599724896836314,
  "selfLinks": 6,
  "averagePathLength": 2.3742937692543795,
  "decentralized_num_paths_found": 943,
  "decentralized_num_paths_missing": 57,
  "decentralized_average_decentralized_path_length": 35.1219512195122,
  "decentralized_average_num_unique_nodes": 21.837751855779427,
  "hierarchy_num_nodes": 385,
  "hierarchy_num_levels": 4,
  "path_length_10_percentile": 3,
  "path_length_20_percentile": 5,
  "path_length_30_percentile": 6,
  "path_length_40_percentile": 8,
  "path_length_50_percentile": 10,
  "path_length_60_percentile": 15,
  "path_length_70_percentile": 30,
  "path_length_80_percentile": 53,
  "path_length_90_percentile": 106,
  "random_num_paths_found": 968,
  "random_num_paths_missing": 32,
  "random_average_decentralized_path_length": 137.57231404958677,
  "random_average_num_unique_nodes": 109.37190082644628
}